myfirstpkg2412/__init__.py
myfirstpkg2412/findAdel.py
myfirstpkg2412-0.1.1.dist-info/METADATA
myfirstpkg2412-0.1.1.dist-info/WHEEL
myfirstpkg2412-0.1.1.dist-info/top_level.txt
myfirstpkg2412-0.1.1.dist-info/RECORD
