Metadata-Version: 2.1
Name: myfirstpkg2412
Version: 0.1.1
Summary: A sample Python package hhhhh 2024年12月07日21:48:15
Home-page: https://github.com/yourusername/myfirstpkg
Author: lys
Author-email: your.email@example.com
Classifier: Programming Language :: Python :: 3
Classifier: License :: OSI Approved :: MIT License
Classifier: Operating System :: OS Independent
Requires-Python: >=3.6
